dapr_microservice_cli/__init__.py
dapr_microservice_cli/__main__.py
dapr_microservice_cli/run.py
dapr_microservice_cli/commands/__init__.py
dapr_microservice_cli/commands/project.py
dapr_microservice_cli/templates/python/fastapi/.gitignore
dapr_microservice_cli/templates/python/fastapi/Dockerfile
dapr_microservice_cli/templates/python/fastapi/Makefile
dapr_microservice_cli/templates/python/fastapi/README.md
dapr_microservice_cli/templates/python/fastapi/requirements.txt
dapr_microservice_cli/templates/python/fastapi/.vscode/launch.json
dapr_microservice_cli/templates/python/fastapi/.vscode/settings.json
dapr_microservice_cli/templates/python/fastapi/config/dev.yaml
dapr_microservice_cli/templates/python/fastapi/config/prod.yaml
dapr_microservice_cli/templates/python/fastapi/doc/alembic.md
dapr_microservice_cli/templates/python/fastapi/doc/api.http
dapr_microservice_cli/templates/python/fastapi/doc/sqlalchemy.md
dapr_microservice_cli/templates/python/fastapi/doc/api/api.http
dapr_microservice_cli/templates/python/fastapi/service/config.py
dapr_microservice_cli/templates/python/fastapi/service/deps.py
dapr_microservice_cli/templates/python/fastapi/service/main.py
dapr_microservice_cli/templates/python/fastapi/service/models.py
dapr_microservice_cli/templates/python/fastapi/service/routers.py
dapr_microservice_cli/templates/python/fastapi/service/schemas.py
dapr_microservice_cli/templates/python/fastapi/tests/service_test.py
dapr_microservice_cli-0.0.2.dist-info/LICENSE
dapr_microservice_cli-0.0.2.dist-info/METADATA
dapr_microservice_cli-0.0.2.dist-info/WHEEL
dapr_microservice_cli-0.0.2.dist-info/entry_points.txt
dapr_microservice_cli-0.0.2.dist-info/top_level.txt
dapr_microservice_cli-0.0.2.dist-info/RECORD
