Metadata-Version: 2.1
Name: dapr-microservice-cli
Version: 0.0.2
Summary: dapr microservice cli
Home-page: UNKNOWN
Author: li1234yun
Author-email: li1234yun@163.com
License: UNKNOWN
Platform: UNKNOWN
Classifier: Programming Language :: Python :: 3
Classifier: License :: OSI Approved :: MIT License
Classifier: Operating System :: OS Independent
Requires-Python: >=3.6
License-File: LICENSE
Requires-Dist: click (>="7.0.0")
